mongokit/__init__.py
mongokit/auth.py
mongokit/collection.py
mongokit/connection.py
mongokit/cursor.py
mongokit/database.py
mongokit/document.py
mongokit/grid.py
mongokit/helpers.py
mongokit/master_slave_connection.py
mongokit/migration.py
mongokit/mongo_exceptions.py
mongokit/operators.py
mongokit/paginator.py
mongokit/schema_document.py
mongokit/versioned_document.py
mongokit_py3k-0.9.1.4.dist-info/AUTHORS
mongokit_py3k-0.9.1.4.dist-info/LICENSE
mongokit_py3k-0.9.1.4.dist-info/METADATA
mongokit_py3k-0.9.1.4.dist-info/WHEEL
mongokit_py3k-0.9.1.4.dist-info/top_level.txt
mongokit_py3k-0.9.1.4.dist-info/RECORD
